dialoghelper/__init__.py
dialoghelper/_modidx.py
dialoghelper/capture.py
dialoghelper/core.py
dialoghelper/db_dc.py
dialoghelper/screenshot.js
dialoghelper/stdtools.py
dialoghelper/tmux.py
dialoghelper/tracetools.py
dialoghelper-0.1.18.dist-info/licenses/LICENSE
dialoghelper-0.1.18.dist-info/METADATA
dialoghelper-0.1.18.dist-info/WHEEL
dialoghelper-0.1.18.dist-info/entry_points.txt
dialoghelper-0.1.18.dist-info/top_level.txt
dialoghelper-0.1.18.dist-info/RECORD
