Metadata-Version: 2.4
Name: dialoghelper
Version: 0.1.18
Summary: Helper functions for solveit dialogs
Home-page: https://github.com/AnswerDotAI/dialoghelper
Author: Jeremy Howard
Author-email: github@jhoward.fastmail.fm
License: Apache Software License 2.0
Keywords: nbdev jupyter notebook python
Classifier: Development Status :: 4 - Beta
Classifier: Intended Audience :: Developers
Classifier: Natural Language :: English
Classifier: Programming Language :: Python :: 3.10
Classifier: Programming Language :: Python :: 3.11
Classifier: Programming Language :: Python :: 3.12
Classifier: License :: OSI Approved :: Apache Software License
Requires-Python: >=3.10
License-File: LICENSE
Requires-Dist: fastcore>=1.11.3
Requires-Dist: ghapi
Requires-Dist: ipykernel-helper>=0.0.28
Requires-Dist: ast-grep-cli
Requires-Dist: ast-grep-py
Requires-Dist: MonsterUI
Requires-Dist: lisette>=0.0.13
Requires-Dist: pillow
Requires-Dist: toolslm>=0.3.26
Provides-Extra: dev
Requires-Dist: python-fasthtml; extra == "dev"
Requires-Dist: tracefunc; extra == "dev"
Dynamic: author
Dynamic: author-email
Dynamic: classifier
Dynamic: description
Dynamic: description-content-type
Dynamic: home-page
Dynamic: keywords
Dynamic: license
Dynamic: license-file
Dynamic: provides-extra
Dynamic: requires-dist
Dynamic: requires-python
Dynamic: summary
